core/__init__.py
core/apps.py
core/middleware.py
django_allow_healthchecks-0.1.0.dist-info/AUTHORS.md
django_allow_healthchecks-0.1.0.dist-info/LICENSE
django_allow_healthchecks-0.1.0.dist-info/METADATA
django_allow_healthchecks-0.1.0.dist-info/WHEEL
django_allow_healthchecks-0.1.0.dist-info/top_level.txt
django_allow_healthchecks-0.1.0.dist-info/RECORD
